{
  "id": "submission-1733254800000-example123",
  "submittedAt": "2025-10-03T18:00:00.000Z",
  "timestamp": 1733254800000,
  "answers": {
    "current_crm": "Rei black book",
    "phone_system": "rei black book",
    "task_management": "NA",
    "project_management": "NA",
    "website_url": "Carrot Website",
    "ppl_providers": "None",
    "email_provider": "Gmail",
    "automation_tools": "NA",
    "overflow_call_center": "NA",
    "device_type": "Iphone",
    "physical_mail": "Doing Direct Mail",
    "company_legal_name_ein": "81-3390650",
    "contract_templates": "No",
    "system_access": "na",
    "migrate_dead_leads": "na",
    "migrate_sequences": "na",
    "migrate_tasks": "na",
    "migrate_notes": "na",
    "unique_systems": "na",
    "team_size_roles": "1",
    "lead_distribution": "na",
    "after_hours_routing": "na",
    "excited_features": "na",
    "unused_features": "E-sgnature",
    "critical_date": "NA",
    "slowest_busiest_days": "NA",
    "specific_workflows": "NA",
    "kpis": "NA",
    "dashboards_reports": "NA",
    "area_codes": "he has 5 phone numbers -",
    "youtube_channel": "NA",
    "demo_company": "NA",
    "training_sessions": "NA"
  }
}
